Workbook

Sheet Prospectos
A1: # | B1: Nicho | C1: Prioridad | D1: Empresa | E1: Web | F1: Qué venden / ticket | G1: Decisor | H1: Contacto | I1: Problema de la web (por confirmar) | J1: Evidencia de negocio fuerte | K1: Gancho (ES) | L1: Estado | M1: Fecha contacto | N1: Canal | O1: Respuesta | P1: Notas
A2: 1 | B2: Bufetes de abogados | C2: A | D2: Delvalle & Delvalle | E2: https://www.delvallepanama.com | F2: Offshore: sociedades, fundaciones de interés privado, cuentas bancarias, bienes raíces vía estructuras | G2: Benjamín Delvalle (socio) | H2: info@delvallepanama.com (genérico); LinkedIn linkedin.com/in/benjamin-delvalle-4324666; +507 390-2890 | I2: Páginas .html estáticas con slugs llenos de keywords; dos dominios (delvallepanama.com y delvalledelvalle.com) que dividen la marca; sin reseñas en Google | J2: Fundada 2004; departamento de clientes extranjeros desde 2006; 15+ años asesorando clientes internacionales | K2: Un inversionista que busca una fundación de interés privado llega a una página .html de 2010 con el nombre de la firma repetido ocho veces, y se va a la siguiente pestaña. | L2: Pendiente
A3: 2 | B3: Bufetes de abogados | C3: A | D3: Chen Lee y Asociados | E3: https://www.chenleeyasociados.com | F3: Sociedades offshore y locales, fundaciones, apertura de cuentas, visas y residencia, bienes raíces | G3: Carlos Antonio Ortega Espinosa (abogado principal) | H3: Solo formulario web; X @ServicioLegal; The Century Tower piso 4 | I3: Sitio .html estático; versión en inglés como páginas sueltas (about-us-en.html) en vez de un idioma real; español primero | J3: Fundada 2009; 11-50 empleados; vende sociedad + banca + migración al extranjero (alto valor por cliente) | K3: Su página en inglés es una copia aparte de la versión en español, y Google no sabe cuál mostrarle al cliente en Miami. | L3: Pendiente
A4: 3 | B4: Bufetes de abogados | C4: A | D4: Mata & Pitti | E4: https://www.matapitti.com | F4: Sociedades offshore, fundaciones, registro de naves y yates, marítimo, residencia | G4: Francisco Javier Mata Donado y Lourdes Pitti Sagrera (socios fundadores) | H4: Sin correo directo público; LinkedIn linkedin.com/in/franciscojaviermatadonado; Torre Advanced, Calle Ricardo Arias | I4: WordPress antiguo; casi cero reseñas (última de 2017); redes sociales inactivas | J4: Fundada 1984; 40+ años; clientela internacional; registro de yates = ticket alto | K4: Cuarenta años de trayectoria y cero reseñas en Google: el cliente extranjero no tiene cómo saber que ustedes existen desde 1984. | L4: Pendiente
A5: 4 | B5: Bufetes de abogados | C5: A | D5: PTY Lawyers | E5: https://www.ptylawyers.com | F5: Migración para expats, bienes raíces, sociedades, fundaciones, planificación patrimonial | G5: Tanya Coronado (fundadora) | H5: tanyacoronado@ptylawyers.com (DIRECTO); +507 213-0012; oficinas en Bella Vista y Gorgona | I5: URLs de constructor antiguo (/practice_area); un blog viejo en WordPress.com sigue posicionando para su contacto; sin reseñas Google visibles | J5: Desde 2009; dos oficinas (ciudad + playa); fundadora preside Origen Real Estate; conferencista en eventos de Playacommunity | K5: El expat de Coronado la conoce por los eventos de Playacommunity, pero cuando la busca en Google aparece primero un blog de WordPress.com de hace años. | L5: Pendiente
A6: 5 | B6: Bufetes de abogados | C6: A | D6: Kovalenko & Vera | E6: https://kovalenkovera.com | F6: Migración, sociedades, bienes raíces, impuestos, PI, registro naviero para clientes internacionales | G6: Colón Eloy Vera (socio, migración) | H6: Solo formulario; +507 6252-2149; Plaza Banco General piso 24 | I6: WordPress con todas las URLs en español aunque venden a extranjeros; sin reseñas | J6: Fundada 2004; equipo de 9; red aeuropea.com; clientes rusos, europeos y expats | K6: Venden a inversionistas extranjeros, pero cada URL de su sitio está en español: el cliente ruso o canadiense ni siquiera llega a la página correcta. | L6: Pendiente
A7: 6 | B7: Bufetes de abogados | C7: B | D7: International Relocation Firm | E7: https://www.relofirm.com | F7: Migración, relocation, bienes raíces, ciudadanía, corporativo, marítimo | G7: Carmen Ortiz (socia senior); Chris Marcel Seguí | H7: Sin correo directo público | I7: Presencia fragmentada (www + legal.relofirm.com); URLs con guion bajo; Google 4.2 con 74 reseñas y quejas repetidas por falta de comunicación | J7: 20+ años; 15 abogados y expertos en relocation; 74 reseñas = volumen real | K7: Tienen 74 reseñas y las malas dicen lo mismo: 'nadie me respondió'. Eso no es un problema legal, es un problema de seguimiento automatizable. | L7: Pendiente
A8: 7 | B8: Bufetes de abogados | C8: B | D8: NDM Law Firm & Associates | E8: https://www.ndm.com.pa | F8: Migración y residencia, offshore, corporativo, impuestos, familia | G8: Melva Herrera y Amarilis Chávez (socias fundadoras); Nisim Lici (gerente general) | H8: Sin correo directo público | I8: Tres estructuras de URL distintas conviviendo (varios rediseños a medias); sin reseñas visibles | J8: 17 años; socios en LatAm, Norteamérica, Europa y Asia; miembro de Justinian Lawyers | K8: Su sitio tiene tres estructuras de URL distintas conviviendo: cada rediseño a medias le cuesta posicionamiento frente a firmas más nuevas. | L8: Pendiente
A9: 8 | B9: Bufetes de abogados | C9: B | D9: J. Quijano | E9: https://jquijano.com | F9: Corporativo, migración, laboral, marítimo | G9: Jorge A. Quijano R. (fundador y socio director) | H9: Sin correo directo público; 4 abogados | I9: WordPress bilingüe; la marca choca online con Quijano & Associates (quijano.com, 1959), mucho más grande | J9: 14+ años como firma; fundador con 20+ años; clientela corporativa y marítima | K9: Cuando un cliente busca 'Quijano abogados Panamá', Google le entrega la firma grande de 1959, no la suya. | L9: Pendiente
A10: 9 | B10: Bufetes de abogados | C10: B | D10: PGS Attorneys | E10: https://www.panamags.com/en/ | F10: Corporativo, migración, bienes raíces, litigios, planificación patrimonial; inmobiliaria hermana | G10: Emilio Cornejo V. (socio fundador); Miguel A. Domínguez (socio director) | H10: Sin correo directo público; Samuel Lewis y Calle 56 | I10: El título indexado en Google dice 'PSG Legal' (error de tipeo de PGS); marca partida en dos dominios (panamags.com y pgs.legal) | J10: Fundada 2008; 25 personas; miembro de Alliott Global Alliance; personal senior de EEUU, Canadá y UK | K10: El título de su página principal en Google dice 'PSG' en vez de 'PGS': la primera impresión que da la firma es un error de tipeo. | L10: Pendiente
A11: 10 | B11: Bufetes de abogados | C11: B | D11: Kraemer & Kraemer | E11: https://kraemerlaw.com/en/home/ | F11: Negocios, impuestos, bienes raíces, migración para inversionistas extranjeros | G11: Marcos Kraemer (fundador) | H11: Sin correo directo público; Calle 50, PH Plaza 2000 piso 17; también Bocas del Toro | I11: Web probablemente la mejor de la lista: pitch de IA / atención 24-7, no rediseño | J11: Fundada 2008; 4.9/5 con 63 reseñas; Client Champion 2021; 2,000+ clientes internacionales | K11: Con 2,000 clientes atendidos y 4.9 estrellas, cada consulta que entra de noche desde Europa debería recibir respuesta en un minuto, no al día siguiente. | L11: Pendiente
A12: 11 | B12: Bienes raíces de lujo | C12: A | D12: Casa Solution (Boquete) | E12: https://www.casasolution.com/ | F12: Casas de montaña, fincas de café y terrenos en Boquete (US$150K a US$1M+) | G12: Jason Cohen (CEO y propietario) | H12: Sin correo directo; oficina 6611-6049; LinkedIn linkedin.com/company/casa-solution | I12: El título de la web en Google es literalmente 'Boquete Office 6611.6049'; WordPress con URLs ?p=; www y no-www indexados a la vez; títulos de listados de 300+ caracteres | J12: Afirma vender más que todas las demás agencias de Boquete juntas; Best of Boquete 2017-2019; decenas de reseñas con nombre; Business Insider y Luxury Latin America | K12: Son la agencia número uno de Boquete, pero el título de su web en Google dice 'Boquete Office 6611.6049' en vez de Casa Solution: están regalando su marca en cada búsqueda. | L12: Pendiente
A13: 12 | B13: Bienes raíces de lujo | C13: A | D13: Grupo Valor Development | E13: https://valordevelopment.com.pa/en/home-english-valor/ | F13: Torres de lujo en preventa: Celeste, Corotú y Guayacán en Santa María; Alamar en Buenaventura; Casco, Costa del Este, Venao (US$360K a US$2M) | G13: Jorge Gallo (fundador y presidente); Fabrizio Guerrero (cofundador) | H13: LinkedIn pa.linkedin.com/in/jorge-gallo-b1019621; sin correo directo | I13: Home en inglés vive en /en/home-english-valor/ (traducción WPML descuidada); higiene de URLs amateur para una marca de US$2M por unidad | J13: 250,000 m² de vivienda estrato 5-6 en una década; prensa en La Prensa, Semana, Axxis; alianza con Cemex; JV con Buenaventura | K13: Venden apartamentos de hasta 2 millones en Santa María, pero su página en inglés vive en /home-english-valor/: la experiencia digital no está a la altura de Guayacán ni de Celeste. | L13: Pendiente
... A63: 62 | B63: Turismo de alta gama | C63: C | D63: Tranquilo Bay Eco Adventure Lodge (Bastimentos) | E63: https://tranquilobay.com | F63: Eco lodge todo incluido en reserva privada de 200 acres (US$306-336 por persona/día) | G63: Jim y Renée Kimball, Jay Viola (fundadores) | H63: Sin correo directo | I63: Web más fuerte del grupo: pitch de automatización de consultas y reservas | J63: TA 5/5 (215 reseñas); TrustScore 4.9 (1,046); Scuba Diving mag | K63: Su web ya vende bien; lo que falta es que responda y califique consultas las 24 horas sin que Jim o Renée tengan que dejar al huésped. | L63: Pendiente

Sheet Fáciles
A1: # | B1: Nicho | C1: Facilidad | D1: Empresa / persona | E1: Web | F1: Instagram | G1: WhatsApp / contacto | H1: Decisor | I1: Ya pagan por leads | J1: Evidencia | K1: Gancho (ES) | L1: Estado | M1: Fecha contacto | N1: Canal | O1: Respuesta | P1: Notas
A2: 1 | B2: Autos seminuevos premium | C2: 1 · Muy fácil | D2: DV Motors (Costa del Este) | E2: dvmotors.co | F2: @dvmotors.pty | G2: +507 6683-7836; sales@dvmotors.co | H2: No identificado (dealer boutique, dueño presente) | I2: Listados premium en encuentra24 (BMW X5, M4, Mercedes, Audi Q8); consignación y trade-in | J2: 29 unidades en showroom; horario L-S 9-18 | K2: 29 carros en showroom y una sola línea de WhatsApp que cierra a las 6 pm: los leads de la noche y el domingo nadie los califica. | L2: Pendiente
A3: 2 | B3: Autos seminuevos premium | C3: 1 · Muy fácil | D3: Luxury Garage Panamá + Luxury Motors Panamá (San Francisco, misma dirección) | E3: luxurygaragepanama.com / luxurymotorspanama.com | F3: @luxurygaragepanama (5.2K) | G3: +507 6094-1911 / 6678-3330; tel 229-0628; info@luxurygaragepanama.com | H3: No identificado (tratar ambas marcas como un solo dueño hasta confirmar) | I3: Perfil encuentra24 con 3 páginas de anuncios; consignación | J3: Inventario Aston Martin, Ferrari, Lamborghini, Porsche; Facebook con cero reseñas; correo Gmail en una de las dos | K3: Venden Ferraris y Maseratis pero su Facebook no tiene ni una reseña y la web no tiene bot: el comprador de 80 mil escribe de noche y le contestan al día siguiente. | L3: Pendiente
A4: 3 | B4: Autos seminuevos premium | C4: 1 · Muy fácil | D4: UsadosPanama.com (Lumovil, Calle 50 Marbella) | E4: usadospanama.com | F4: @usadospanama1 (24K) | G4: WhatsApp 6426-6361; tel 214-4700; asolis@panarental.com (gerente) | H4: A. Solís (gerente, ligado a Panarental) | I4: Sección Promociones en la web; asesoría de financiamiento | J4: Fundada 2018; también taller | K4: Tienen promos en la web y 24K seguidores, pero el WhatsApp es un celular: los leads de las promos se pierden en el mismo chat del taller. | L4: Pendiente
A5: 4 | B5: Autos seminuevos premium | C5: 1 · Muy fácil | D5: Bottenhorn Premium Car Dealership (Costa del Este) | E5: bottenhornpa.com | F5: @bottenhornpa; TikTok; YouTube | G5: +507 6895-3232; info@bottenhornpa.com | H5: Vladimir Bottenhorn (fundador y CEO, ex BMW) | I5: encuentra24 activo; financiamiento; 'mayor inventario de autos europeos de Panamá' | J5: Más de una década; negocio familiar; atiende solo por cita privada | K5: Atienden solo por cita privada: cada mensaje de Instagram que no se responde en 10 minutos es un BMW que se va a otro showroom de Costa del Este. | L5: Pendiente
A6: 5 | B6: Mejoras del hogar (alto ticket) | C6: 1 · Muy fácil | D6: Cocinas y Muebles Panamá (cocinas, closets, puertas) | E6: sin web / solo Instagram | F6: @cocinasymueblespanama (9K) | G6: 6350-4551 (en la bio) | H6: No identificado | I6: Bio de IG = 'cotiza al 6350-4551'; todo el embudo es Instagram a WhatsApp | J6: Sin web ni Google Business fuerte | K6: Todo el negocio vive en una bio de Instagram: sin web, y el 6350-4551 contesta solo cuando el dueño no está midiendo una cocina. | L6: Pendiente
A7: 6 | B7: Mejoras del hogar (alto ticket) | C7: 1 · Muy fácil | D7: Profil Glass (cabinas de baño, barandas, ventanas) | E7: profilglasspty.com | F7: @profilglasspty | G7: +507 6430-6553; tel 391-8589 | H7: No identificado (Río Abajo, Plaza Gaudiano) | I7: Web dice literalmente 'escríbenos por WhatsApp con medidas aproximadas'; horario L-S 8am-10pm | J7: 15+ años; portafolio en web | K7: Su propia web dice 'manda las medidas por WhatsApp': un asistente que las pida, precotice y agende la visita les ahorra las 14 horas de chat diario. | L7: Pendiente
A8: 7 | B8: Mejoras del hogar (alto ticket) | C8: 1 · Muy fácil | D8: Rapid Pools / Grupo Rapid (piscinas, jacuzzis) | E8: rapid-pools.com / gruporapid.com | F8: n/d | G8: +507 6114-9653 | H8: Gilberto Urrutia (owner, LinkedIn) | I8: Botón 'Solicitar cotización' a WhatsApp; distribuidor Hayward; 3 sucursales (Panamá, Río Hato, David) | J8: 100+ clientes activos; grupo con Rapid Frío y Rapid Pest | K8: Tres sucursales y tres marcas (piscinas, aire, fumigación) compartiendo un solo WhatsApp: cada lead de piscina de 20 mil compite con una queja de fumigación. | L8: Pendiente
A9: 8 | B9: Mejoras del hogar (alto ticket) | C9: 1 · Muy fácil | D9: Casabonitta Design (cocinas, closets, cuarzo) | E9: casabonittadesign.com (básica) | F9: @casabonittadesign (26K) | G9: +507 6278-0450 | H9: No identificado (local en Albrook Mall) | I9: 26K seguidores = inversión fuerte en Instagram; local en mall 10am-8pm | J9: 10+ años | K9: 26 mil seguidores y un local en Albrook, pero cada cotización se pierde en el chat de WhatsApp mientras la web no muestra ni precios ni agenda. | L9: Pendiente
A10: 9 | B10: Instaladores solares | C10: 1 · Muy fácil | D10: Solar Power Pat S.A. (Los Pueblos) | E10: solarpowerpat.net | F10: FB solar.powerpat; X @SPowerPat; YouTube | G10: 6646-3171; gcomercial@solarpowerpat.com | H10: Angelo Patiño (fundador y GM desde 2014; LinkedIn) | I10: Landings SEO por ciudad; promo financiamiento 0%; robot de limpieza SolarCleano | J10: Desde 2014; Canadian Solar / Jinko | K10: Publican horario L-V 8-17: el lead de Instagram que escribe viernes noche o sábado no recibe respuesta hasta el lunes. | L10: Pendiente
A11: 10 | B11: Instaladores solares | C11: 1 · Muy fácil | D11: Energiza Panamá | E11: energizapanama.com | F11: @energiza_panama (2.8K) | G11: +507 6208-3614; energizapanama@gmail.com | H11: No identificado (sociedad de ~5 años) | I11: Instagram activo; financiamiento flexible; trámites con ENSA/Naturgy como argumento | J11: Desde 2018 | K11: Correo en Gmail y ventas por Instagram: cada DM se contesta a mano y no hay seguimiento al que pidió cotización y no cerró. | L11: Pendiente
A12: 11 | B12: Instaladores solares | C12: 1 · Muy fácil | D12: Potencia Solar (Las Mañanitas, Panamá Este) | E12: potenciasolarinc.com | F12: n/d | G12: 6440-6680; potenciasolar2025@gmail.com | H12: No identificado (empresa nueva 2025) | I12: Proceso 'escríbenos al WhatsApp con tu factura, propuesta, visita técnica' | J12: Nueva 2025; tramitan planos fotovoltaicos | K12: Empresa nueva que depende 100% del WhatsApp: el flujo 'envía tu factura' es exactamente lo que un asistente IA hace 24/7 y agenda la visita. | L12: Pendiente
A13: 12 | B13: Instaladores solares | C13: 1 · Muy fácil | D13: Powerlink Solar (Av. 5 Sur y Calle 76) | E13: powerlink.solar | F13: @powerlink.solar (1.5K) | G13: +507 6288-8940; tel 6295-8694 | H13: Camilo Amado (CEO; LinkedIn) | I13: Mucho contenido SEO ('precio panel solar'); financiamiento propio; casos de éxito | J13: 30 años en ingeniería eléctrica; comercial hasta 486 paneles | K13: Invierten en SEO y financiamiento propio pero el WhatsApp es un celular: nadie califica el lead ni le pide la factura automáticamente. | L13: Pendiente
... A61: 60 | B61: Agentes y alquiler corto | C61: 3 · Después | D61: Realtor Panamá (@panamarealtor) · agente | E61: sin web | F61: @panamarealtor (2.3K) | G61: +507 6149-1542 | H61: No identificado | I61: IG como canal principal | J61: n/d | K61: Todo su embudo vive en la bio de Instagram; una web de marca personal más un asistente convierte el DM en cita. | L61: Pendiente

Sheet Resumen
A1: Resumen de prospectos
A3: Nicho | B3: A | C3: B | D3: C | E3: Total | F3: Contactados | G3: Respondieron
A4: Bufetes de abogados | B4: =COUNTIFS(Prospectos!$B:$B,$A4,Prospectos!$C:$C,"A") | C4: =COUNTIFS(Prospectos!$B:$B,$A4,Prospectos!$C:$C,"B") | D4: =COUNTIFS(Prospectos!$B:$B,$A4,Prospectos!$C:$C,"C") | E4: =SUM(B4:D4) | F4: =COUNTIFS(Prospectos!$B:$B,$A4,Prospectos!$L:$L,"Contactado")+COUNTIFS(Prospectos!$B:$B,$A4,Prospectos!$L:$L,"Respondió")+COUNTIFS(Prospectos!$B:$B,$A4,Prospectos!$L:$L,"Reunión")+COUNTIFS(Prospectos!$B:$B,$A4,Prospectos!$L:$L,"Cliente") | G4: =COUNTIFS(Prospectos!$B:$B,$A4,Prospectos!$L:$L,"Respondió")+COUNTIFS(Prospectos!$B:$B,$A4,Prospectos!$L:$L,"Reunión")+COUNTIFS(Prospectos!$B:$B,$A4,Prospectos!$L:$L,"Cliente")
A5: Bienes raíces de lujo | B5: =COUNTIFS(Prospectos!$B:$B,$A5,Prospectos!$C:$C,"A") | C5: =COUNTIFS(Prospectos!$B:$B,$A5,Prospectos!$C:$C,"B") | D5: =COUNTIFS(Prospectos!$B:$B,$A5,Prospectos!$C:$C,"C") | E5: =SUM(B5:D5) | F5: =COUNTIFS(Prospectos!$B:$B,$A5,Prospectos!$L:$L,"Contactado")+COUNTIFS(Prospectos!$B:$B,$A5,Prospectos!$L:$L,"Respondió")+COUNTIFS(Prospectos!$B:$B,$A5,Prospectos!$L:$L,"Reunión")+COUNTIFS(Prospectos!$B:$B,$A5,Prospectos!$L:$L,"Cliente") | G5: =COUNTIFS(Prospectos!$B:$B,$A5,Prospectos!$L:$L,"Respondió")+COUNTIFS(Prospectos!$B:$B,$A5,Prospectos!$L:$L,"Reunión")+COUNTIFS(Prospectos!$B:$B,$A5,Prospectos!$L:$L,"Cliente")
A6: Clínicas privadas | B6: =COUNTIFS(Prospectos!$B:$B,$A6,Prospectos!$C:$C,"A") | C6: =COUNTIFS(Prospectos!$B:$B,$A6,Prospectos!$C:$C,"B") | D6: =COUNTIFS(Prospectos!$B:$B,$A6,Prospectos!$C:$C,"C") | E6: =SUM(B6:D6) | F6: =COUNTIFS(Prospectos!$B:$B,$A6,Prospectos!$L:$L,"Contactado")+COUNTIFS(Prospectos!$B:$B,$A6,Prospectos!$L:$L,"Respondió")+COUNTIFS(Prospectos!$B:$B,$A6,Prospectos!$L:$L,"Reunión")+COUNTIFS(Prospectos!$B:$B,$A6,Prospectos!$L:$L,"Cliente") | G6: =COUNTIFS(Prospectos!$B:$B,$A6,Prospectos!$L:$L,"Respondió")+COUNTIFS(Prospectos!$B:$B,$A6,Prospectos!$L:$L,"Reunión")+COUNTIFS(Prospectos!$B:$B,$A6,Prospectos!$L:$L,"Cliente")
A7: Arquitectura e interiorismo | B7: =COUNTIFS(Prospectos!$B:$B,$A7,Prospectos!$C:$C,"A") | C7: =COUNTIFS(Prospectos!$B:$B,$A7,Prospectos!$C:$C,"B") | D7: =COUNTIFS(Prospectos!$B:$B,$A7,Prospectos!$C:$C,"C") | E7: =SUM(B7:D7) | F7: =COUNTIFS(Prospectos!$B:$B,$A7,Prospectos!$L:$L,"Contactado")+COUNTIFS(Prospectos!$B:$B,$A7,Prospectos!$L:$L,"Respondió")+COUNTIFS(Prospectos!$B:$B,$A7,Prospectos!$L:$L,"Reunión")+COUNTIFS(Prospectos!$B:$B,$A7,Prospectos!$L:$L,"Cliente") | G7: =COUNTIFS(Prospectos!$B:$B,$A7,Prospectos!$L:$L,"Respondió")+COUNTIFS(Prospectos!$B:$B,$A7,Prospectos!$L:$L,"Reunión")+COUNTIFS(Prospectos!$B:$B,$A7,Prospectos!$L:$L,"Cliente")
A8: Gestión patrimonial y fiduciarias | B8: =COUNTIFS(Prospectos!$B:$B,$A8,Prospectos!$C:$C,"A") | C8: =COUNTIFS(Prospectos!$B:$B,$A8,Prospectos!$C:$C,"B") | D8: =COUNTIFS(Prospectos!$B:$B,$A8,Prospectos!$C:$C,"C") | E8: =SUM(B8:D8) | F8: =COUNTIFS(Prospectos!$B:$B,$A8,Prospectos!$L:$L,"Contactado")+COUNTIFS(Prospectos!$B:$B,$A8,Prospectos!$L:$L,"Respondió")+COUNTIFS(Prospectos!$B:$B,$A8,Prospectos!$L:$L,"Reunión")+COUNTIFS(Prospectos!$B:$B,$A8,Prospectos!$L:$L,"Cliente") | G8: =COUNTIFS(Prospectos!$B:$B,$A8,Prospectos!$L:$L,"Respondió")+COUNTIFS(Prospectos!$B:$B,$A8,Prospectos!$L:$L,"Reunión")+COUNTIFS(Prospectos!$B:$B,$A8,Prospectos!$L:$L,"Cliente")
A9: Turismo de alta gama | B9: =COUNTIFS(Prospectos!$B:$B,$A9,Prospectos!$C:$C,"A") | C9: =COUNTIFS(Prospectos!$B:$B,$A9,Prospectos!$C:$C,"B") | D9: =COUNTIFS(Prospectos!$B:$B,$A9,Prospectos!$C:$C,"C") | E9: =SUM(B9:D9) | F9: =COUNTIFS(Prospectos!$B:$B,$A9,Prospectos!$L:$L,"Contactado")+COUNTIFS(Prospectos!$B:$B,$A9,Prospectos!$L:$L,"Respondió")+COUNTIFS(Prospectos!$B:$B,$A9,Prospectos!$L:$L,"Reunión")+COUNTIFS(Prospectos!$B:$B,$A9,Prospectos!$L:$L,"Cliente") | G9: =COUNTIFS(Prospectos!$B:$B,$A9,Prospectos!$L:$L,"Respondió")+COUNTIFS(Prospectos!$B:$B,$A9,Prospectos!$L:$L,"Reunión")+COUNTIFS(Prospectos!$B:$B,$A9,Prospectos!$L:$L,"Cliente")
A10: Total | B10: =SUM(B4:B9) | C10: =SUM(C4:C9) | D10: =SUM(D4:D9) | E10: =SUM(E4:E9) | F10: =SUM(F4:F9) | G10: =SUM(G4:G9)
A12: Tasa de respuesta | B12: =IF(F10=0,0,G10/F10)
A15: Prospectos fáciles (hoja Fáciles)
A16: Nicho | B16: 1 Muy fácil | C16: 2 Fácil | D16: 3 Después | E16: Total | F16: Contactados | G16: Respondieron
A17: Autos seminuevos premium | B17: =COUNTIFS(Fáciles!$B:$B,$A17,Fáciles!$C:$C,"1 · Muy fácil") | C17: =COUNTIFS(Fáciles!$B:$B,$A17,Fáciles!$C:$C,"2 · Fácil") | D17: =COUNTIFS(Fáciles!$B:$B,$A17,Fáciles!$C:$C,"3 · Después") | E17: =SUM(B17:D17) | F17: =COUNTIFS(Fáciles!$B:$B,$A17,Fáciles!$L:$L,"Contactado")+COUNTIFS(Fáciles!$B:$B,$A17,Fáciles!$L:$L,"Respondió")+COUNTIFS(Fáciles!$B:$B,$A17,Fáciles!$L:$L,"Reunión")+COUNTIFS(Fáciles!$B:$B,$A17,Fáciles!$L:$L,"Cliente") | G17: =COUNTIFS(Fáciles!$B:$B,$A17,Fáciles!$L:$L,"Respondió")+COUNTIFS(Fáciles!$B:$B,$A17,Fáciles!$L:$L,"Reunión")+COUNTIFS(Fáciles!$B:$B,$A17,Fáciles!$L:$L,"Cliente")
A18: Mejoras del hogar (alto ticket) | B18: =COUNTIFS(Fáciles!$B:$B,$A18,Fáciles!$C:$C,"1 · Muy fácil") | C18: =COUNTIFS(Fáciles!$B:$B,$A18,Fáciles!$C:$C,"2 · Fácil") | D18: =COUNTIFS(Fáciles!$B:$B,$A18,Fáciles!$C:$C,"3 · Después") | E18: =SUM(B18:D18) | F18: =COUNTIFS(Fáciles!$B:$B,$A18,Fáciles!$L:$L,"Contactado")+COUNTIFS(Fáciles!$B:$B,$A18,Fáciles!$L:$L,"Respondió")+COUNTIFS(Fáciles!$B:$B,$A18,Fáciles!$L:$L,"Reunión")+COUNTIFS(Fáciles!$B:$B,$A18,Fáciles!$L:$L,"Cliente") | G18: =COUNTIFS(Fáciles!$B:$B,$A18,Fáciles!$L:$L,"Respondió")+COUNTIFS(Fáciles!$B:$B,$A18,Fáciles!$L:$L,"Reunión")+COUNTIFS(Fáciles!$B:$B,$A18,Fáciles!$L:$L,"Cliente")
A19: Instaladores solares | B19: =COUNTIFS(Fáciles!$B:$B,$A19,Fáciles!$C:$C,"1 · Muy fácil") | C19: =COUNTIFS(Fáciles!$B:$B,$A19,Fáciles!$C:$C,"2 · Fácil") | D19: =COUNTIFS(Fáciles!$B:$B,$A19,Fáciles!$C:$C,"3 · Después") | E19: =SUM(B19:D19) | F19: =COUNTIFS(Fáciles!$B:$B,$A19,Fáciles!$L:$L,"Contactado")+COUNTIFS(Fáciles!$B:$B,$A19,Fáciles!$L:$L,"Respondió")+COUNTIFS(Fáciles!$B:$B,$A19,Fáciles!$L:$L,"Reunión")+COUNTIFS(Fáciles!$B:$B,$A19,Fáciles!$L:$L,"Cliente") | G19: =COUNTIFS(Fáciles!$B:$B,$A19,Fáciles!$L:$L,"Respondió")+COUNTIFS(Fáciles!$B:$B,$A19,Fáciles!$L:$L,"Reunión")+COUNTIFS(Fáciles!$B:$B,$A19,Fáciles!$L:$L,"Cliente")
A20: Bodas y eventos | B20: =COUNTIFS(Fáciles!$B:$B,$A20,Fáciles!$C:$C,"1 · Muy fácil") | C20: =COUNTIFS(Fáciles!$B:$B,$A20,Fáciles!$C:$C,"2 · Fácil") | D20: =COUNTIFS(Fáciles!$B:$B,$A20,Fáciles!$C:$C,"3 · Después") | E20: =SUM(B20:D20) | F20: =COUNTIFS(Fáciles!$B:$B,$A20,Fáciles!$L:$L,"Contactado")+COUNTIFS(Fáciles!$B:$B,$A20,Fáciles!$L:$L,"Respondió")+COUNTIFS(Fáciles!$B:$B,$A20,Fáciles!$L:$L,"Reunión")+COUNTIFS(Fáciles!$B:$B,$A20,Fáciles!$L:$L,"Cliente") | G20: =COUNTIFS(Fáciles!$B:$B,$A20,Fáciles!$L:$L,"Respondió")+COUNTIFS(Fáciles!$B:$B,$A20,Fáciles!$L:$L,"Reunión")+COUNTIFS(Fáciles!$B:$B,$A20,Fáciles!$L:$L,"Cliente")
A21: Agentes y alquiler corto | B21: =COUNTIFS(Fáciles!$B:$B,$A21,Fáciles!$C:$C,"1 · Muy fácil") | C21: =COUNTIFS(Fáciles!$B:$B,$A21,Fáciles!$C:$C,"2 · Fácil") | D21: =COUNTIFS(Fáciles!$B:$B,$A21,Fáciles!$C:$C,"3 · Después") | E21: =SUM(B21:D21) | F21: =COUNTIFS(Fáciles!$B:$B,$A21,Fáciles!$L:$L,"Contactado")+COUNTIFS(Fáciles!$B:$B,$A21,Fáciles!$L:$L,"Respondió")+COUNTIFS(Fáciles!$B:$B,$A21,Fáciles!$L:$L,"Reunión")+COUNTIFS(Fáciles!$B:$B,$A21,Fáciles!$L:$L,"Cliente") | G21: =COUNTIFS(Fáciles!$B:$B,$A21,Fáciles!$L:$L,"Respondió")+COUNTIFS(Fáciles!$B:$B,$A21,Fáciles!$L:$L,"Reunión")+COUNTIFS(Fáciles!$B:$B,$A21,Fáciles!$L:$L,"Cliente")
A22: Total | B22: =SUM(B17:B21) | C22: =SUM(C17:C21) | D22: =SUM(D17:D21) | E22: =SUM(E17:E21) | F22: =SUM(F17:F21) | G22: =SUM(G17:G21)
A23: Tasa de respuesta | B23: =IF(F22=0,0,G22/F22)

Sheet Cómo usar
A1: Cómo usar esta lista
A3: 1. Prioridad A = negocio fuerte con web débil. Son los candidatos para hacer mockup y escribir con el método del Panama Dive Center.
A4: 2. Prioridad B = negocio fuerte con web aceptable. No vender rediseño: vender el asistente de IA (WhatsApp 24/7, agenda, recordatorios, reactivación).
A5: 3. Prioridad C = secundarios. Verificar antes de invertir tiempo.
A7: Antes de escribir a cualquiera, abrir su web 30 segundos y confirmar la columna 'Problema de la web':
A8: - Año del copyright en el footer
A9: - Cómo se ve en el móvil
A10: - Candado SSL (https)
A11: - Si tiene inglés / español
A12: - Si tiene reservas o agenda en línea
A13: Esas señales se infirieron de URLs y títulos indexados en Google, porque esta sesión no pudo cargar las webs directamente. Las empresas, decisores y ganchos sí están verificados por búsqueda.
A15: Las columnas amarillas (Estado, Fecha contacto, Canal, Respuesta, Notas) son las que se llenan a mano. La hoja Resumen se actualiza sola.
... A35: Los números de WhatsApp vienen de bios, encuentra24 y webs; confirmar en el perfil antes del primer mensaje.
